mcubes-0.1.6.dist-info/METADATA
mcubes-0.1.6.dist-info/WHEEL
mcubes-0.1.6.dist-info/licenses/PYPI_LICENSE
mcubes/__init__.py
mcubes/mcubes.abi3.so
mcubes-0.1.6.dist-info/RECORD
