Metadata-Version: 2.4
Name: mcubes
Version: 0.1.6
Classifier: Programming Language :: Rust
Classifier: Programming Language :: Python :: Implementation :: CPython
Classifier: Programming Language :: Python :: Implementation :: PyPy
License-File: PYPI_LICENSE
Summary: The Marching Cubes algorithm for creating isosurfaces
Author-email: David O'Connor <the_alchemist@fastmail.com>
Requires-Python: >=3.10
